phylogenetic/__init__.py
phylogenetic/features.py
phylogenetic_features-0.1.dist-info/LICENSE
phylogenetic_features-0.1.dist-info/METADATA
phylogenetic_features-0.1.dist-info/WHEEL
phylogenetic_features-0.1.dist-info/top_level.txt
phylogenetic_features-0.1.dist-info/RECORD
