Metadata-Version: 2.1
Name: phylogenetic-features
Version: 0.1
Summary: A package to extract phylogenetic features
Home-page: https://github.com/Dowingows/phylogenetic_features
Author: Domingos Dias
Author-email: domingos.adj@nca.ufma.br
License: UNKNOWN
Platform: UNKNOWN
Classifier: Programming Language :: Python :: 3
Classifier: License :: OSI Approved :: MIT License
Classifier: Operating System :: OS Independent
